jira_batch_create/__init__.py
jira_batch_create/adf.py
jira_batch_create/creator.py
jira_batch_create/setup_logging.py
jira_batch_create-0.2.4.dist-info/METADATA
jira_batch_create-0.2.4.dist-info/WHEEL
jira_batch_create-0.2.4.dist-info/top_level.txt
jira_batch_create-0.2.4.dist-info/RECORD
